yaylib/__init__.py
yaylib/api/__init__.py
yaylib/api/auth.py
yaylib/api/call.py
yaylib/api/chat.py
yaylib/api/group.py
yaylib/api/misc.py
yaylib/api/notification.py
yaylib/api/post.py
yaylib/api/review.py
yaylib/api/thread.py
yaylib/api/user.py
yaylib/client.py
yaylib/config.py
yaylib/constants.py
yaylib/device.py
yaylib/errors.py
yaylib/models.py
yaylib/responses.py
yaylib/state.py
yaylib/utils.py
yaylib/ws.py
yaylib-1.5.4.dist-info/LICENSE
yaylib-1.5.4.dist-info/METADATA
yaylib-1.5.4.dist-info/WHEEL
yaylib-1.5.4.dist-info/RECORD
