Metadata-Version: 2.3
Name: yaylib
Version: 1.5.4
Summary: 同世代と趣味の通話コミュニティ - Yay! (イェイ) で投稿やタイムラインの取得、リツイートやいいねの実行、フォローや投稿の検索など様々な機能をPythonプログラムから利用可能なAPIクライアントツールです。
License: MIT
Keywords: yay,yaylib,api,bot,tool,client,library,wrapper,ボット,ライブラリ,ツール
Author: ekkx
Author-email: nikola.desuga@gmail.com
Requires-Python: >=3.10,<3.14
Classifier: License :: OSI Approved :: MIT License
Classifier: Programming Language :: Python :: 3
Classifier: Programming Language :: Python :: 3.10
Classifier: Programming Language :: Python :: 3.11
Classifier: Programming Language :: Python :: 3.12
Classifier: Programming Language :: Python :: 3.13
Requires-Dist: aiohttp (>=3.11.0,<4.0.0)
Requires-Dist: cryptography (>=44.0.0,<45.0.0)
Requires-Dist: pillow (>=11.2.0,<12.0.0)
Project-URL: Homepage, https://github.com/ekkx/yaylib
Project-URL: Repository, https://github.com/ekkx/yaylib
